SDasBasicCalculator/__init__.py
SDasBasicCalculator-1.0.1.dist-info/LICENSE.txt
SDasBasicCalculator-1.0.1.dist-info/METADATA
SDasBasicCalculator-1.0.1.dist-info/WHEEL
SDasBasicCalculator-1.0.1.dist-info/top_level.txt
SDasBasicCalculator-1.0.1.dist-info/RECORD
