Metadata-Version: 2.1
Name: SDasBasicCalculator
Version: 1.0.1
Summary: A very basic calculator
Home-page: UNKNOWN
Author: Subhayan Das
Author-email: nips.subhayan@gmail.com
License: MIT
Keywords: calculator
Platform: UNKNOWN
Classifier: Development Status :: 5 - Production/Stable
Classifier: Intended Audience :: Education
Classifier: Operating System :: Microsoft :: Windows :: Windows 10
Classifier: License :: OSI Approved :: MIT License
Classifier: Programming Language :: Python :: 3
Provides-Extra: dev
Requires-Dist: pytest (>=3.7) ; extra == 'dev'
